LICENSE
MANIFEST.in
README.md
setup.cfg
setup.py
django_dev_admin/__init__.py
django_dev_admin/middleware.py
django_dev_admin.egg-info/PKG-INFO
django_dev_admin.egg-info/SOURCES.txt
django_dev_admin.egg-info/dependency_links.txt
django_dev_admin.egg-info/top_level.txt
django_dev_admin/__pycache__/__init__.cpython-36.pyc
django_dev_admin/__pycache__/middleware.cpython-36.pyc
django_dev_admin/management/__init__.py
django_dev_admin/management/commands/_logic.py
django_dev_admin/management/commands/login_as.py
django_dev_admin/management/commands/__pycache__/_logic.cpython-36.pyc
django_dev_admin/management/commands/__pycache__/login_as.cpython-36.pyc