Metadata-Version: 2.1
Name: django-dev-admin
Version: 1.2.0
Summary: A Django app to help developers login to any user via django command.
Home-page: https://github.com/smithkre/django-dev-admin
Author: Smith Krengkrud
Author-email: smith.kre@gmail.com
License: BSD 3
Keywords: django dev admin helper
Platform: UNKNOWN
Classifier: Environment :: Web Environment
Classifier: Intended Audience :: Developers
Classifier: Operating System :: OS Independent
Classifier: Programming Language :: Python
Classifier: Framework :: Django
Classifier: Topic :: Utilities
